opencc_jieba_pyo3-0.7.2.dist-info/METADATA
opencc_jieba_pyo3-0.7.2.dist-info/WHEEL
opencc_jieba_pyo3-0.7.2.dist-info/entry_points.txt
opencc_jieba_pyo3-0.7.2.dist-info/licenses/LICENSE
opencc_jieba_pyo3/__init__.py
opencc_jieba_pyo3/__main__.py
opencc_jieba_pyo3/office_helper.py
opencc_jieba_pyo3/opencc_jieba_pyo3.pyd
opencc_jieba_pyo3/opencc_jieba_pyo3.pyi
opencc_jieba_pyo3-0.7.2.dist-info/RECORD
